bandcrash/__init__.py
bandcrash/cdda.py
bandcrash/cli.py
bandcrash/gui/__init__.py
bandcrash/gui/datatypes.py
bandcrash/gui/encoder.py
bandcrash/gui/file_utils.py
bandcrash/gui/track_editor.py
bandcrash/gui/widgets.py
bandcrash/images.py
bandcrash/options.py
bandcrash/players/camptown.py
bandcrash/util.py
bandcrash-0.9.5.dist-info/LICENSE
bandcrash-0.9.5.dist-info/METADATA
bandcrash-0.9.5.dist-info/WHEEL
bandcrash-0.9.5.dist-info/entry_points.txt
bandcrash-0.9.5.dist-info/RECORD
