Metadata-Version: 2.3
Name: bandcrash
Version: 0.9.5
Summary: Tools for publishing albums to the web and digital stores
License: MIT
Author: fluffy
Author-email: fluffy@beesbuzz.biz
Requires-Python: >=3.11,<3.14
Classifier: License :: OSI Approved :: MIT License
Classifier: Programming Language :: Python :: 3
Classifier: Programming Language :: Python :: 3.11
Classifier: Programming Language :: Python :: 3.12
Classifier: Programming Language :: Python :: 3.13
Provides-Extra: gui
Requires-Dist: camptown (>=0.3.7,<0.4.0)
Requires-Dist: chardet (>=4.0.0,<5.0.0)
Requires-Dist: mutagen (>=1.45.1,<2.0.0)
Requires-Dist: pillow (>=11.3.0,<12.0.0)
Requires-Dist: pyffmpeg (>=2.4.2.18.1,<3.0.0.0.0)
Requires-Dist: pyside6 (>=6.8,<6.9) ; extra == "gui"
Requires-Dist: unidecode (>=1.3.8,<2.0.0)
Project-URL: Documentation, https://bandcrash.readthedocs.io/
Project-URL: Repository, https://github.com/fluffy-critter/bandcrash
